stream_converter-1.0.0.dist-info/METADATA
stream_converter-1.0.0.dist-info/WHEEL
stream_converter/__init__.py
stream_converter/conversion_function.py
stream_converter/converter.py
stream_converter/microphone_stream.py
stream_converter-1.0.0.dist-info/RECORD
