Metadata-Version: 2.1
Name: stream_converter
Version: 1.0.0
Summary: A package for applying real-time transformations on streaming data.
Author-Email: Matt Zhang <set.stun@gmail.com>
License: MIT
Requires-Python: >=3.8
Requires-Dist: pyaudio>=0.2.14
Requires-Dist: build>=1.0.3
